vega_datasets/__init__.py
vega_datasets/core.py
vega_datasets/dataset_info.json
vega_datasets/datasets.json
vega_datasets/local_datasets.json
vega_datasets/utils.py
vega_datasets/_data/airports.csv
vega_datasets/_data/anscombe.json
vega_datasets/_data/barley.json
vega_datasets/_data/burtin.json
vega_datasets/_data/cars.json
vega_datasets/_data/crimea.json
vega_datasets/_data/driving.json
vega_datasets/_data/iowa-electricity.csv
vega_datasets/_data/iris.json
vega_datasets/_data/la-riots.csv
vega_datasets/_data/ohlc.json
vega_datasets/_data/seattle-temps.csv
vega_datasets/_data/seattle-weather.csv
vega_datasets/_data/sf-temps.csv
vega_datasets/_data/stocks.csv
vega_datasets/_data/us-employment.csv
vega_datasets/_data/wheat.json
vega_datasets/tests/__init__.py
vega_datasets/tests/test_core.py
vega_datasets/tests/test_download.py
vega_datasets/tests/test_errors.py
vega_datasets/tests/test_local_datasets.py
vega_datasets/tests/test_metadata.py
vega_datasets-0.9.0.dist-info/LICENSE
vega_datasets-0.9.0.dist-info/METADATA
vega_datasets-0.9.0.dist-info/WHEEL
vega_datasets-0.9.0.dist-info/top_level.txt
vega_datasets-0.9.0.dist-info/RECORD
