Metadata-Version: 2.1
Name: vega-datasets
Version: 0.9.0
Summary: A Python package for offline access to Vega datasets
Home-page: http://github.com/altair-viz/vega_datasets
Author: Jake VanderPlas
Author-email: jakevdp@gmail.com
Maintainer: Jake VanderPlas
Maintainer-email: jakevdp@gmail.com
License: MIT
Download-URL: http://github.com/altair-viz/vega_datasets
Project-URL: Bug Reports, https://github.com/altair-viz/vega_datasets/issues
Project-URL: Source, https://github.com/altair-viz/vega_datasets
Platform: UNKNOWN
Classifier: Development Status :: 4 - Beta
Classifier: Environment :: Console
Classifier: Intended Audience :: Science/Research
Classifier: License :: OSI Approved :: MIT License
Classifier: Natural Language :: English
Classifier: Programming Language :: Python :: 3.5
Classifier: Programming Language :: Python :: 3.6
Classifier: Programming Language :: Python :: 3.7
Classifier: Programming Language :: Python :: 3.8
Requires-Python: >=3.5
